<?xml version="1.0" ?><osoby><Osoba><imie>Kazimiera</imie><nazwisko>Szczuka</nazwisko><wiek>38</wiek><eMail>kazia@odwazne.pl</eMail></Osoba><Osoba><imie>Kazimiera</imie><nazwisko>Cycuszek</nazwisko><wiek>38</wiek><eMail>kazia@odwazne.pl</eMail></Osoba><Osoba><imie>Kazimiera</imie><nazwisko>Szczuka</nazwisko><wiek>38</wiek><eMail>kazia@odwazne.pl</eMail></Osoba><Osoba><imie>Kazimiera</imie><nazwisko>Szczuka</nazwisko><wiek>38</wiek><eMail>kazia@odwazne.pl</eMail></Osoba><Osoba><imie>Kazimiera</imie><nazwisko>Szczuka</nazwisko><wiek>38</wiek><eMail>kazia@odwazne.pl</eMail></Osoba><Osoba><imie>Kazimiera</imie><nazwisko>Cycuszek</nazwisko><wiek>38</wiek><eMail>kazia@odwazne.pl</eMail></Osoba><Osoba><imie>Kazimiera</imie><nazwisko>Szczuka</nazwisko><wiek>38</wiek><eMail>kazia@odwazne.pl</eMail></Osoba><Osoba><imie>Kazimiera</imie><nazwisko>Szczuka</nazwisko><wiek>38</wiek><eMail>kazia@odwazne.pl</eMail></Osoba><Osoba><imie>Kazimiera</imie><nazwisko>Szczuka</nazwisko><wiek>38</wiek><eMail>kazia@odwazne.pl</eMail></Osoba><Osoba><imie>Kazimiera</imie><nazwisko>Cycuszek</nazwisko><wiek>38</wiek><eMail>kazia@odwazne.pl</eMail></Osoba><Osoba><imie>Kazimiera</imie><nazwisko>Szczuka</nazwisko><wiek>38</wiek><eMail>kazia@odwazne.pl</eMail></Osoba><Osoba><imie>Kazimiera</imie><nazwisko>Szczuka</nazwisko><wiek>38</wiek><eMail>kazia@odwazne.pl</eMail></Osoba><Osoba><imie>Kazimiera</imie><nazwisko>Szczuka</nazwisko><wiek>38</wiek><eMail>kazia@odwazne.pl</eMail></Osoba><Osoba><imie>Kazimiera</imie><nazwisko>Cycuszek</nazwisko><wiek>38</wiek><eMail>kazia@odwazne.pl</eMail></Osoba><Osoba><imie>Kazimiera</imie><nazwisko>Szczuka</nazwisko><wiek>38</wiek><eMail>kazia@odwazne.pl</eMail></Osoba><Osoba><imie>Kazimiera</imie><nazwisko>Szczuka</nazwisko><wiek>38</wiek><eMail>kazia@odwazne.pl</eMail></Osoba><Osoba><imie>Kazimiera</imie><nazwisko>Szczuka</nazwisko><wiek>38</wiek><eMail>kazia@odwazne.pl</eMail></Osoba><Osoba><imie>Kazimiera</imie><nazwisko>Cycuszek</nazwisko><wiek>38</wiek><eMail>kazia@odwazne.pl</eMail></Osoba><Osoba><imie>Kazimiera</imie><nazwisko>Szczuka</nazwisko><wiek>38</wiek><eMail>kazia@odwazne.pl</eMail></Osoba><Osoba><imie>Kazimiera</imie><nazwisko>Szczuka</nazwisko><wiek>38</wiek><eMail>kazia@odwazne.pl</eMail></Osoba><Osoba><imie>Kazimiera</imie><nazwisko>Szczuka</nazwisko><wiek>38</wiek><eMail>kazia@odwazne.pl</eMail></Osoba><Osoba><imie>Kazimiera</imie><nazwisko>Cycuszek</nazwisko><wiek>38</wiek><eMail>kazia@odwazne.pl</eMail></Osoba><Osoba><imie>Kazimiera</imie><nazwisko>Szczuka</nazwisko><wiek>38</wiek><eMail>kazia@odwazne.pl</eMail></Osoba><Osoba><imie>Kazimiera</imie><nazwisko>Szczuka</nazwisko><wiek>38</wiek><eMail>kazia@odwazne.pl</eMail></Osoba><Osoba><imie>Kazimiera</imie><nazwisko>Szczuka</nazwisko><wiek>38</wiek><eMail>kazia@odwazne.pl</eMail></Osoba><Osoba><imie>Kazimiera</imie><nazwisko>Cycuszek</nazwisko><wiek>38</wiek><eMail>kazia@odwazne.pl</eMail></Osoba><Osoba><imie>Kazimiera</imie><nazwisko>Szczuka</nazwisko><wiek>38</wiek><eMail>kazia@odwazne.pl</eMail></Osoba><Osoba><imie>Kazimiera</imie><nazwisko>Szczuka</nazwisko><wiek>38</wiek><eMail>kazia@odwazne.pl</eMail></Osoba><Osoba><imie>Kazimiera</imie><nazwisko>Szczuka</nazwisko><wiek>38</wiek><eMail>kazia@odwazne.pl</eMail></Osoba><Osoba><imie>Kazimiera</imie><nazwisko>Cycuszek</nazwisko><wiek>38</wiek><eMail>kazia@odwazne.pl</eMail></Osoba><Osoba><imie>Kazimiera</imie><nazwisko>Szczuka</nazwisko><wiek>38</wiek><eMail>kazia@odwazne.pl</eMail></Osoba><Osoba><imie>Kazimiera</imie><nazwisko>Szczuka</nazwisko><wiek>38</wiek><eMail>kazia@odwazne.pl</eMail></Osoba><Osoba><imie>Kazimiera</imie><nazwisko>Szczuka</nazwisko><wiek>38</wiek><eMail>kazia@odwazne.pl</eMail></Osoba><Osoba><imie>Kazimiera</imie><nazwisko>Cycuszek</nazwisko><wiek>38</wiek><eMail>kazia@odwazne.pl</eMail></Osoba><Osoba><imie>Kazimiera</imie><nazwisko>Szczuka</nazwisko><wiek>38</wiek><eMail>kazia@odwazne.pl</eMail></Osoba><Osoba><imie>Kazimiera</imie><nazwisko>Szczuka</nazwisko><wiek>38</wiek><eMail>kazia@odwazne.pl</eMail></Osoba><Osoba><imie>Kazimiera</imie><nazwisko>Szczuka</nazwisko><wiek>38</wiek><eMail>kazia@odwazne.pl</eMail></Osoba><Osoba><imie>Kazimiera</imie><nazwisko>Cycuszek</nazwisko><wiek>38</wiek><eMail>kazia@odwazne.pl</eMail></Osoba><Osoba><imie>Kazimiera</imie><nazwisko>Szczuka</nazwisko><wiek>38</wiek><eMail>kazia@odwazne.pl</eMail></Osoba><Osoba><imie>Kazimiera</imie><nazwisko>Szczuka</nazwisko><wiek>38</wiek><eMail>kazia@odwazne.pl</eMail></Osoba><Osoba><imie>Kazimiera</imie><nazwisko>Szczuka</nazwisko><wiek>38</wiek><eMail>kazia@odwazne.pl</eMail></Osoba><Osoba><imie>Kazimiera</imie><nazwisko>Cycuszek</nazwisko><wiek>38</wiek><eMail>kazia@odwazne.pl</eMail></Osoba><Osoba><imie>Kazimiera</imie><nazwisko>Szczuka</nazwisko><wiek>38</wiek><eMail>kazia@odwazne.pl</eMail></Osoba><Osoba><imie>Kazimiera</imie><nazwisko>Szczuka</nazwisko><wiek>38</wiek><eMail>kazia@odwazne.pl</eMail></Osoba><Osoba><imie>Kazimiera</imie><nazwisko>Szczuka</nazwisko><wiek>38</wiek><eMail>kazia@odwazne.pl</eMail></Osoba><Osoba><imie>Kazimiera</imie><nazwisko>Cycuszek</nazwisko><wiek>38</wiek><eMail>kazia@odwazne.pl</eMail></Osoba><Osoba><imie>Kazimiera</imie><nazwisko>Szczuka</nazwisko><wiek>38</wiek><eMail>kazia@odwazne.pl</eMail></Osoba><Osoba><imie>Kazimiera</imie><nazwisko>Szczuka</nazwisko><wiek>38</wiek><eMail>kazia@odwazne.pl</eMail></Osoba></osoby>